pyicloudng/__init__.py
pyicloudng/base.py
pyicloudng/cmdline.py
pyicloudng/exceptions.py
pyicloudng/main.py
pyicloudng/utils.py
pyicloudng/services/__init__.py
pyicloudng/services/account.py
pyicloudng/services/calendar.py
pyicloudng/services/contacts.py
pyicloudng/services/drive.py
pyicloudng/services/findmyiphone.py
pyicloudng/services/photos.py
pyicloudng/services/reminders.py
pyicloudng/services/ubiquity.py
pyicloudng-0.0.1.dist-info/LICENSE
pyicloudng-0.0.1.dist-info/METADATA
pyicloudng-0.0.1.dist-info/WHEEL
pyicloudng-0.0.1.dist-info/entry_points.txt
pyicloudng-0.0.1.dist-info/top_level.txt
pyicloudng-0.0.1.dist-info/RECORD
